setup.py
distributex/__init__.py
distributex/service.py
distributex.egg-info/PKG-INFO
distributex.egg-info/SOURCES.txt
distributex.egg-info/dependency_links.txt
distributex.egg-info/requires.txt
distributex.egg-info/top_level.txt
twisted/plugins/distributex_plugin.py